bisslog_pymongo/__init__.py
bisslog_pymongo/exception_handler.py
bisslog_pymongo/pymongo_helper.py
bisslog_pymongo-0.0.1.dist-info/licenses/LICENSE
bisslog_pymongo-0.0.1.dist-info/METADATA
bisslog_pymongo-0.0.1.dist-info/WHEEL
bisslog_pymongo-0.0.1.dist-info/top_level.txt
bisslog_pymongo-0.0.1.dist-info/RECORD
