Metadata-Version: 2.4
Name: bisslog_pymongo
Version: 0.0.1
Summary: It is an extension of the bisslog library to support processes with the pymongo driver library of the mongo db database.
Author-email: Darwin Stiven Herrera Cartagena <darwinsherrerac@gmail.com>
Project-URL: Homepage, https://github.com/darwinhc/bisslog-pymongo
Keywords: hexagonal,adapters,pymongo
Classifier: Programming Language :: Python :: 3
Classifier: Operating System :: OS Independent
Requires-Python: >=3.7
License-File: LICENSE
Dynamic: license-file
